PyWallpaper.py
setup.py
PyWallpaper.egg-info/PKG-INFO
PyWallpaper.egg-info/SOURCES.txt
PyWallpaper.egg-info/dependency_links.txt
PyWallpaper.egg-info/top_level.txt