Metadata-Version: 1.1
Name: PyWallpaper
Version: 1.0.0
Summary: Cross Platform Python module to change wallpaper
Home-page: https://github.com/geekpradd/PyWallpaper
Author: Pradipta Bora
Author-email: pradd@outlook.com
License: MIT
Keywords: wallpaper
Platform: UNKNOWN
Classifier: Development Status :: 5 - Production/Stable
Classifier: Topic :: Utilities
Classifier: License :: OSI Approved :: MIT License
Classifier: Operating System :: OS Independent
Classifier: Programming Language :: Python
